siina/__init__.py
siina/core.py
siina/dzt.py
siina/filters.py
siina/rd3.py
siina-19.8.28.dist-info/LICENSE
siina-19.8.28.dist-info/METADATA
siina-19.8.28.dist-info/WHEEL
siina-19.8.28.dist-info/top_level.txt
siina-19.8.28.dist-info/RECORD
